{
  "count": 1,
  "generated_at": "2026-07-06T07:00:55Z",
  "name_key": "ourmine",
  "results": [
    {
      "actor_id": "misp-2c9e1964-9357-11e9-ad8f-5f422851e912",
      "canonical_name": "OurMine",
      "misp_uuid": "2c9e1964-9357-11e9-ad8f-5f422851e912",
      "mitre_id": null,
      "naming_sources": [
        "MISP Galaxy"
      ],
      "primary_source": "misp-galaxy",
      "search_names": [
        "OurMine"
      ],
      "source_ids": [
        "external-reference",
        "misp-galaxy"
      ],
      "url": "api/v1/actors/misp-2c9e1964-9357-11e9-ad8f-5f422851e912.json",
      "web_url": "?actor=misp-2c9e1964-9357-11e9-ad8f-5f422851e912"
    }
  ]
}
