{
  "count": 1,
  "generated_at": "2026-07-20T05:58:54Z",
  "query_key": "953ff7c8c07a49b486711d7d5f59129c",
  "results": [
    {
      "actor_id": "misp-953ff7c8-c07a-49b4-8671-1d7d5f59129c",
      "canonical_name": "Amaranth-Dragon",
      "misp_uuid": "953ff7c8-c07a-49b4-8671-1d7d5f59129c",
      "mitre_id": null,
      "naming_sources": [
        "MISP Galaxy"
      ],
      "primary_source": "misp-galaxy",
      "search_names": [
        "Amaranth-Dragon"
      ],
      "source_ids": [
        "external-reference",
        "misp-galaxy"
      ],
      "url": "api/v1/actors/misp-953ff7c8-c07a-49b4-8671-1d7d5f59129c.json",
      "web_url": "?actor=misp-953ff7c8-c07a-49b4-8671-1d7d5f59129c"
    }
  ]
}
