{
  "count": 1,
  "generated_at": "2026-07-02T05:52:38Z",
  "query_key": "conquerorselectronicarmy",
  "results": [
    {
      "actor_id": "misp-20912a84-43b0-4fad-a30b-9ee3253da721",
      "canonical_name": "Conquerors Electronic Army",
      "misp_uuid": "20912a84-43b0-4fad-a30b-9ee3253da721",
      "mitre_id": null,
      "naming_sources": [
        "MISP Galaxy"
      ],
      "primary_source": "misp-galaxy",
      "search_names": [
        "Conquerors Electronic Army"
      ],
      "source_ids": [
        "external-reference",
        "misp-galaxy"
      ],
      "url": "api/v1/actors/misp-20912a84-43b0-4fad-a30b-9ee3253da721.json",
      "web_url": "?actor=misp-20912a84-43b0-4fad-a30b-9ee3253da721"
    }
  ]
}
