{
  "count": 1,
  "generated_at": "2026-07-06T07:00:55Z",
  "query_key": "handala",
  "results": [
    {
      "actor_id": "misp-7b14f285-86e9-47da-be1a-16ce566c428b",
      "canonical_name": "Handala",
      "misp_uuid": "7b14f285-86e9-47da-be1a-16ce566c428b",
      "mitre_id": null,
      "naming_sources": [
        "MISP Galaxy"
      ],
      "primary_source": "misp-galaxy",
      "search_names": [
        "Handala"
      ],
      "source_ids": [
        "external-reference",
        "misp-galaxy"
      ],
      "url": "api/v1/actors/misp-7b14f285-86e9-47da-be1a-16ce566c428b.json",
      "web_url": "?actor=misp-7b14f285-86e9-47da-be1a-16ce566c428b"
    }
  ]
}
