{
  "count": 1,
  "generated_at": "2026-07-20T05:58:54Z",
  "query_key": "misp8dda51ef9a3048f7b0fd5b6f0a62262d",
  "results": [
    {
      "actor_id": "misp-8dda51ef-9a30-48f7-b0fd-5b6f0a62262d",
      "canonical_name": "Operation Soft Cell",
      "misp_uuid": "8dda51ef-9a30-48f7-b0fd-5b6f0a62262d",
      "mitre_id": null,
      "naming_sources": [
        "MISP Galaxy"
      ],
      "primary_source": "misp-galaxy",
      "search_names": [
        "Operation Soft Cell"
      ],
      "source_ids": [
        "external-reference",
        "misp-galaxy"
      ],
      "url": "api/v1/actors/misp-8dda51ef-9a30-48f7-b0fd-5b6f0a62262d.json",
      "web_url": "?actor=misp-8dda51ef-9a30-48f7-b0fd-5b6f0a62262d"
    }
  ]
}
