{
  "count": 1,
  "generated_at": "2026-07-20T05:58:54Z",
  "query_key": "mispd35a871f402b4a0ea70204e886abe883",
  "results": [
    {
      "actor_id": "misp-d35a871f-402b-4a0e-a702-04e886abe883",
      "canonical_name": "GopherWhisper",
      "misp_uuid": "d35a871f-402b-4a0e-a702-04e886abe883",
      "mitre_id": null,
      "naming_sources": [
        "MISP Galaxy"
      ],
      "primary_source": "misp-galaxy",
      "search_names": [
        "GopherWhisper"
      ],
      "source_ids": [
        "external-reference",
        "misp-galaxy"
      ],
      "url": "api/v1/actors/misp-d35a871f-402b-4a0e-a702-04e886abe883.json",
      "web_url": "?actor=misp-d35a871f-402b-4a0e-a702-04e886abe883"
    }
  ]
}
