{
  "count": 1,
  "generated_at": "2026-07-20T05:58:54Z",
  "query_key": "misp9ba291f2b107402d90833128395ff26e",
  "results": [
    {
      "actor_id": "misp-9ba291f2-b107-402d-9083-3128395ff26e",
      "canonical_name": "Operation Kabar Cobra",
      "misp_uuid": "9ba291f2-b107-402d-9083-3128395ff26e",
      "mitre_id": null,
      "naming_sources": [
        "MISP Galaxy"
      ],
      "primary_source": "misp-galaxy",
      "search_names": [
        "Operation Kabar Cobra"
      ],
      "source_ids": [
        "external-reference",
        "misp-galaxy"
      ],
      "url": "api/v1/actors/misp-9ba291f2-b107-402d-9083-3128395ff26e.json",
      "web_url": "?actor=misp-9ba291f2-b107-402d-9083-3128395ff26e"
    }
  ]
}
