{
  "count": 1,
  "generated_at": "2026-07-13T05:58:12Z",
  "query_key": "misp7223da4759b44c5c9f97d7ceb5866651",
  "results": [
    {
      "actor_id": "misp-7223da47-59b4-4c5c-9f97-d7ceb5866651",
      "canonical_name": "TA2723",
      "misp_uuid": "7223da47-59b4-4c5c-9f97-d7ceb5866651",
      "mitre_id": null,
      "naming_sources": [
        "MISP Galaxy"
      ],
      "primary_source": "misp-galaxy",
      "search_names": [
        "TA2723"
      ],
      "source_ids": [
        "external-reference",
        "misp-galaxy"
      ],
      "url": "api/v1/actors/misp-7223da47-59b4-4c5c-9f97-d7ceb5866651.json",
      "web_url": "?actor=misp-7223da47-59b4-4c5c-9f97-d7ceb5866651"
    }
  ]
}
