{
  "count": 1,
  "generated_at": "2026-07-06T07:00:55Z",
  "query_key": "moneytaker",
  "results": [
    {
      "actor_id": "misp-7d78ec00-dfdc-4a80-a4da-63f1ae63bd7f",
      "canonical_name": "MoneyTaker",
      "misp_uuid": "7d78ec00-dfdc-4a80-a4da-63f1ae63bd7f",
      "mitre_id": null,
      "naming_sources": [
        "MISP Galaxy"
      ],
      "primary_source": "misp-galaxy",
      "search_names": [
        "MoneyTaker"
      ],
      "source_ids": [
        "external-reference",
        "misp-galaxy"
      ],
      "url": "api/v1/actors/misp-7d78ec00-dfdc-4a80-a4da-63f1ae63bd7f.json",
      "web_url": "?actor=misp-7d78ec00-dfdc-4a80-a4da-63f1ae63bd7f"
    }
  ]
}
